motila/__init__.py
motila/motila.py
motila/utils.py
motila-1.1.0.dist-info/licenses/LICENSE
motila-1.1.0.dist-info/WHEEL
motila-1.1.0.dist-info/METADATA
motila-1.1.0.dist-info/RECORD
