Metadata-Version: 2.4
Name: motila
Version: 1.1.0
Summary: MotilA: A pipeline for microglial motility analysis
Author-email: Fabrizio Musacchio <fabrizio.musacchio@posteo.de>
Requires-Python: >=3.9
License-File: LICENSE
Requires-Dist: numpy
Requires-Dist: scipy
Requires-Dist: matplotlib
Requires-Dist: tifffile
Requires-Dist: scikit-image
Requires-Dist: scikit-learn
Requires-Dist: zarr
Requires-Dist: SimpleITK
Requires-Dist: pystackreg
Requires-Dist: pandas
Requires-Dist: numcodecs
Requires-Dist: openpyxl
Requires-Dist: xlrd
Requires-Dist: ipywidgets
Requires-Dist: ipykernel
Requires-Dist: ipympl
Requires-Dist: pytest ; extra == "dev"
Requires-Dist: pytest-cov ; extra == "dev"
Project-URL: Documentation, https://github.com/fabriziomusacchio/motila#readme
Project-URL: Homepage, https://github.com/fabriziomusacchio/motila
Project-URL: Source, https://github.com/fabriziomusacchio/motila
Project-URL: Tracker, https://github.com/fabriziomusacchio/motila/issues
Provides-Extra: dev
